MANIFEST.in
README.rst
setup.py
stapi/__init__.py
stapi/base.py
stapi/base_response.py
stapi/common_search_criteria.py
stapi/full.py
stapi/full_response.py
stapi/helper.py
stapi/main.py
stapi/rest_client.py
stapi/search_criteria.py
stapi.egg-info/PKG-INFO
stapi.egg-info/SOURCES.txt
stapi.egg-info/dependency_links.txt
stapi.egg-info/not-zip-safe
stapi.egg-info/top_level.txt