Metadata-Version: 1.0
Name: stapi
Version: 0.1.13
Summary: A Python client for accessing Star Trek API
Home-page: https://github.com/mklucz/stapi-python
Author: Maciej Kluczyński
Author-email: maciej.lukasz.kluczynski@gmail.com
License: MIT
Platform: UNKNOWN
